slickqa/__init__.py
slickqa/connection.py
slickqa/data.py
slickqa/queries.py
slickqa/slickqa.py
slickqa/micromodels/__init__.py
slickqa/micromodels/fields.py
slickqa/micromodels/models.py
slickqa/micromodels/packages/__init__.py
slickqa/micromodels/packages/PySO8601/__init__.py
slickqa/micromodels/packages/PySO8601/__version__.py
slickqa/micromodels/packages/PySO8601/datetimestamps.py
slickqa/micromodels/packages/PySO8601/durations.py
slickqa/micromodels/packages/PySO8601/intervals.py
slickqa/micromodels/packages/PySO8601/timezones.py
slickqa/micromodels/packages/PySO8601/utility.py
slickqa/tests/__init__.py
slickqa/tests/micromodels.py
slickqa-2.0.686.dist-info/LICENSE.txt
slickqa-2.0.686.dist-info/METADATA
slickqa-2.0.686.dist-info/WHEEL
slickqa-2.0.686.dist-info/top_level.txt
slickqa-2.0.686.dist-info/RECORD
