Metadata-Version: 2.1
Name: slickqa
Version: 2.0.686
Summary: A client library for the Slick QA result database
Home-page: http://github.com/slickqa/python-client
Author: Slick Developers
Author-email: UNKNOWN
License: License :: OSI Approved :: Apache Software License
Platform: UNKNOWN
Requires-Dist: requests (>=1.1.0)
Requires-Dist: docutils
Requires-Dist: simplejson
